{
  "collapse-filter": false,
  "search": "",
  "showTags": false,
  "showAttachments": false,
  "hideUnresolved": false,
  "showOrphans": false,
  "collapse-color-groups": false,
  "colorGroups": [
    {
      "query": "tag:#MOC",
      "color": {
        "a": 1,
        "rgb": 16223685
      }
    },
    {
      "query": "tag:#Note",
      "color": {
        "a": 1,
        "rgb": 14069084
      }
    }
  ],
  "collapse-display": false,
  "showArrow": false,
  "textFadeMultiplier": 0,
  "nodeSizeMultiplier": 1,
  "lineSizeMultiplier": 1,
  "collapse-forces": false,
  "centerStrength": 0.518713248970312,
  "repelStrength": 10,
  "linkStrength": 1,
  "linkDistance": 250,
  "scale": 1.3075200885936666,
  "close": false
}